{"date":"2026-07-16","last_updated":"2026-07-17T07:33:15Z","status":"validated","site":{"total_users":9478,"new_users":null,"sessions":12159,"engaged_sessions":null,"engagement_rate":null,"funnel_entrants":1300,"purchases":147,"revenue":175778.50,"purchase_conversion_rate":11.31},"devices":{"desktop":1181,"mobile":8259,"tablet":51},"channels":{"direct":5672,"organic_search":1727,"ppc":1248,"paid_social":198,"unassigned":49,"referral":502,"other":66},"overall_funnel":{"vehicle_details":1300,"quote_loader":968,"quote_list":856,"addons":290,"policy_review":224,"payment_page":202,"purchase":147},"adnoc_funnel":{"landing_page":431,"vehicle_details":143,"quote_loader":85,"quote_list":77,"addons":26,"policy_review":18,"payment_page":18,"purchase":14}}
